ConCorr/GUI.py
ConCorr/__init__.py
ConCorr/main.py
ConCorr/misc.py
ConCorr/version.py
ConCorr/analysis/Correlation_group.py
ConCorr/analysis/Test_script.py
ConCorr/analysis/__init__ .py
ConCorr/analysis/corr_mat.py
ConCorr/analysis/timeseries.py
ConCorr/outputs/CAPs.py
ConCorr/outputs/ELA.py
ConCorr/outputs/__init__.py
ConCorr-0.0.1.dist-info/METADATA
ConCorr-0.0.1.dist-info/WHEEL
ConCorr-0.0.1.dist-info/top_level.txt
ConCorr-0.0.1.dist-info/RECORD
